inter/__init__.py
inter/_client.py
inter/_inter.py
inter/testing.py
bancointer-0.1.1.dist-info/LICENSE
bancointer-0.1.1.dist-info/WHEEL
bancointer-0.1.1.dist-info/METADATA
bancointer-0.1.1.dist-info/RECORD
